{
 "actions": [],
 "allow_rename": 1,
 "creation": "2024-08-21 20:00:22.146763",
 "doctype": "DocType",
 "editable_grid": 1,
 "engine": "InnoDB",
 "field_order": [
  "crew_member"
 ],
 "fields": [
  {
   "fieldname": "crew_member",
   "fieldtype": "Link",
   "label": "Crew member",
   "options": "Crew Member"
  }
 ],
 "index_web_pages_for_search": 1,
 "istable": 1,
 "links": [],
 "modified": "2024-08-21 20:01:37.869519",
 "modified_by": "Administrator",
 "module": "Airport Shop",
 "name": "Crew members",
 "owner": "Administrator",
 "permissions": [],
 "sort_field": "modified",
 "sort_order": "DESC",
 "states": []
}